odoo/addons/iot_amqp/README.rst
odoo/addons/iot_amqp/__init__.py
odoo/addons/iot_amqp/__manifest__.py
odoo/addons/iot_amqp/data/system_data.xml
odoo/addons/iot_amqp/i18n/iot_amqp.pot
odoo/addons/iot_amqp/models/__init__.py
odoo/addons/iot_amqp/models/iot_amqp_host.py
odoo/addons/iot_amqp/models/iot_device_output.py
odoo/addons/iot_amqp/models/iot_device_output_action.py
odoo/addons/iot_amqp/models/iot_system_action.py
odoo/addons/iot_amqp/readme/CONTRIBUTORS.rst
odoo/addons/iot_amqp/readme/DESCRIPTION.rst
odoo/addons/iot_amqp/security/ir.model.access.csv
odoo/addons/iot_amqp/static/description/icon.png
odoo/addons/iot_amqp/static/description/index.html
odoo/addons/iot_amqp/tests/__init__.py
odoo/addons/iot_amqp/tests/test_amqp.py
odoo/addons/iot_amqp/views/iot_amqp_host.xml
odoo/addons/iot_amqp/views/iot_device_output_views.xml
odoo12_addon_iot_amqp-12.0.1.1.1.dist-info/METADATA
odoo12_addon_iot_amqp-12.0.1.1.1.dist-info/WHEEL
odoo12_addon_iot_amqp-12.0.1.1.1.dist-info/top_level.txt
odoo12_addon_iot_amqp-12.0.1.1.1.dist-info/RECORD
